band/__init__.py
band/base.py
band/config.py
band/covert.py
band/layers.py
band/model.py
band/optimization.py
band/progress.py
band/utils.py
band/version.py
band/dataset/__init__.py
band/dataset/chnsenticorp.py
band/dataset/lcqcm.py
band/dataset/masa_ner.py
band/dataset/toxic.py
band/seqeval/__init__.py
band/seqeval/callbacks.py
band/seqeval/metrics/__init__.py
band/seqeval/metrics/sequence_labeling.py
band-0.3.3.dist-info/LICENSE
band-0.3.3.dist-info/METADATA
band-0.3.3.dist-info/WHEEL
band-0.3.3.dist-info/top_level.txt
band-0.3.3.dist-info/RECORD
