Metadata-Version: 2.1
Name: band
Version: 0.3.3
Summary: BERT Application
Home-page: https://github.com/sunyancn/band
Author: sunyancn
Author-email: sunyanhust@163.com
License: MIT License
Platform: UNKNOWN
Classifier: License :: OSI Approved :: Apache Software License
Classifier: Programming Language :: Python :: 3.6
Classifier: Programming Language :: Python :: Implementation :: CPython
Classifier: Programming Language :: Python :: Implementation :: PyPy
Requires-Python: >3.6
Requires-Dist: six
Requires-Dist: tensorflow (==2.0.0)
Requires-Dist: numpy (==1.16.4)
Requires-Dist: pandas (==0.23.4)
Requires-Dist: scikit-learn (>=0.21.1)
Requires-Dist: h5py
Requires-Dist: prettytable
Requires-Dist: tqdm
Requires-Dist: transformers (==2.2.0)
Requires-Dist: nltk (==3.4.5)
Requires-Dist: jieba (==0.39)
Requires-Dist: tabulator (==1.30.0)
